honeycomb/opentelemetry/__init__.py
honeycomb/opentelemetry/baggage.py
honeycomb/opentelemetry/distro.py
honeycomb/opentelemetry/local_exporter.py
honeycomb/opentelemetry/metrics.py
honeycomb/opentelemetry/options.py
honeycomb/opentelemetry/resource.py
honeycomb/opentelemetry/sampler.py
honeycomb/opentelemetry/trace.py
honeycomb/opentelemetry/version.py
honeycomb_opentelemetry-0.1.0.dist-info/entry_points.txt
honeycomb_opentelemetry-0.1.0.dist-info/WHEEL
honeycomb_opentelemetry-0.1.0.dist-info/METADATA
honeycomb_opentelemetry-0.1.0.dist-info/LICENSE
honeycomb_opentelemetry-0.1.0.dist-info/RECORD
