Metadata-Version: 2.1
Name: honeycomb-opentelemetry
Version: 0.1.0
Summary: Honeycomb OpenTelemetry Distro for Python
Author: Honeycomb
Author-email: support@honeycomb.io
Requires-Python: >=3.7.2,<4.0
Classifier: Programming Language :: Python :: 3
Classifier: Programming Language :: Python :: 3.8
Classifier: Programming Language :: Python :: 3.9
Classifier: Programming Language :: Python :: 3.10
Classifier: Programming Language :: Python :: 3.11
Requires-Dist: opentelemetry-api (>=1.14.0,<2.0.0)
Requires-Dist: opentelemetry-exporter-otlp (>=1.14.0,<2.0.0)
Requires-Dist: opentelemetry-instrumentation (>=0.36b0,<0.37)
Requires-Dist: opentelemetry-sdk (>=1.14.0,<2.0.0)
